vvtool/__init__.py
vvtool/application.py
vvtool/cli.py
vvtool/documents.py
vvtool/manager.py
vvtool/migrations/0001_trump.py
vvtool/migrations/__init__.py
vvtool/migrations/data/__init__.py
vvtool/migrations/data/initial_trump_data.xlsx
vvtool/migrations/data/initial_trump_votes.csv
voteview_dev-0.1.5.dist-info/entry_points.txt
voteview_dev-0.1.5.dist-info/LICENSE
voteview_dev-0.1.5.dist-info/WHEEL
voteview_dev-0.1.5.dist-info/METADATA
voteview_dev-0.1.5.dist-info/RECORD
