Metadata-Version: 2.1
Name: voteview-dev
Version: 0.1.5
Summary: Voteview command-line interface
Author: Adam Boche
Author-email: aboche@ucla.edu
Requires-Python: >=3.6,<4.0
Classifier: Programming Language :: Python :: 3
Classifier: Programming Language :: Python :: 3.6
Classifier: Programming Language :: Python :: 3.7
Classifier: Programming Language :: Python :: 3.8
Requires-Dist: alley (==0.0.3)
Requires-Dist: attrs
Requires-Dist: click (>=6.0,<7.0)
Requires-Dist: importlib_resources (==1.0)
Requires-Dist: mongoengine (==0.18.2)
Requires-Dist: pylint (==2.3)
Requires-Dist: pymongo (==3.8)
